llgeo/__init__.py
llgeo/basic_stats/__init__.py
llgeo/basic_stats/corr_horz.py
llgeo/basic_stats/corr_vert.py
llgeo/basic_stats/correlation.py
llgeo/basic_stats/distributions.py
llgeo/basic_stats/markov_chains.py
llgeo/basic_stats/toro_method.py
llgeo/coords/__init__.py
llgeo/coords/transform.py
llgeo/cpt_interp/__init__.py
llgeo/cpt_interp/cpt_interp.py
llgeo/motions/__init__.py
llgeo/motions/spectra.py
llgeo/plotting/__init__.py
llgeo/plotting/mpl.py
llgeo/plotting/prettify.py
llgeo/props_basic/__init__.py
llgeo/props_basic/stress.py
llgeo/props_basic/vs.py
llgeo/props_nonlinear/__init__.py
llgeo/props_nonlinear/darendeli_2011.py
llgeo/quad4m/__init__.py
llgeo/quad4m/db_utils.py
llgeo/quad4m/elemprops.py
llgeo/quad4m/extract_results.py
llgeo/quad4m/genfiles.py
llgeo/quad4m/geometry.py
llgeo/quad4m/parallel.py
llgeo/quad4m/plots_checks.py
llgeo/quad4m/post_process.py
llgeo/quad4m/props_elems.py
llgeo/quad4m/props_nodes.py
llgeo/quad4m/runQ4Ms.py
llgeo/quad4m_geometry/__init__.py
llgeo/quad4m_geometry/dxf_dfs.py
llgeo/rand_fields/LAS.py
llgeo/rand_fields/__init__.py
llgeo/rand_fields/test_save_outputs.py
llgeo/rand_fields/F77_to_py/__init__.py
llgeo/randfields/LAS.py
llgeo/randfields/__init__.py
llgeo/randfields/test_save_outputs.py
llgeo/randfields/F77_to_py/__init__.py
llgeo/templates/__init__.py
llgeo/utilities/__init__.py
llgeo/utilities/check_errors.py
llgeo/utilities/files.py
llgeo/utilities/formatters.py
llgeo/utilities/sensitivity_analysis.py
llgeo-0.0.18.dist-info/LICENSE.py
llgeo-0.0.18.dist-info/METADATA
llgeo-0.0.18.dist-info/WHEEL
llgeo-0.0.18.dist-info/top_level.txt
llgeo-0.0.18.dist-info/RECORD
