Metadata-Version: 2.1
Name: llgeo
Version: 0.0.18
Summary: Python library for Geotechnical Engineering
Home-page: https://github.com/lauralunacabrera/LLGEO.git
Author: Laura Luna
Author-email: lauralunacabrera@gmail.com
License: UNKNOWN
Platform: UNKNOWN
Classifier: Programming Language :: Python :: 3
Classifier: License :: OSI Approved :: MIT License
Classifier: Operating System :: OS Independent
Requires-Python: >=3.7
Requires-Dist: numpy (>=1.16.4)
Requires-Dist: pandas (>=1.1.5)
Requires-Dist: scipy (>=1.2.0)
Requires-Dist: ezdxf (>=0.14.2)
Requires-Dist: matplotlib (>=3.0.3)
Requires-Dist: seaborn (>=0.9.0)
